{
  "_preEvolution": 61,
  "NationalId": 62,
  "CatchRate": 0,
  "MaleDistribution": 0.5,
  "EggGroup1": 2,
  "EggGroup2": 0,
  "Name": "Tartard",
  "Type1": 7,
  "Type2": 3,
  "AverageSize": 0,
  "AverageWeight": 0,
  "XpGain": 230,
  "Description": null,
  "CanSwim": true,
  "CanWalk": true,
  "CanFly": false,
  "CanBeRidden": false,
  "BaseCharacteristic": {
    "LifePoint": 0,
    "Attack": 0,
    "Defense": 0,
    "SpeAttack": 0,
    "SpeDefense": 0,
    "Velocity": 0
  },
  "AvailableTalents": [
    {
	  "$type": "Anjril.PokemonWorld.Common.Index.Talent.FakeTalent",
      "Name": "Talent"
    }
  ],
  "LevelingMoves": "0,Water_Gun",
  "LearnableMoves": "",
  "EvolutionCondition": {
    "$type": "Anjril.PokemonWorld.Common.Index.Evolution.FakeCondition",
    "Fake": true
  }
}